robust_statistics_simulator/__init__.py
robust_statistics_simulator/standard_error.py
robust_statistics_simulator/type_I_error.py
robust_statistics_simulator-0.1.dev2.dist-info/LICENSE
robust_statistics_simulator-0.1.dev2.dist-info/METADATA
robust_statistics_simulator-0.1.dev2.dist-info/WHEEL
robust_statistics_simulator-0.1.dev2.dist-info/top_level.txt
robust_statistics_simulator-0.1.dev2.dist-info/RECORD
