Metadata-Version: 2.1
Name: robust-statistics-simulator
Version: 0.1.dev2
Summary: Interactive simulations that demonstrate properties of robust statistics
Home-page: https://github.com/Alcampopiano/hypothesize
Author: Allan Campopiano
Author-email: campopianoa@hcdsb.org
License: BSD 3-clause
Platform: UNKNOWN
Classifier: Development Status :: 1 - Planning
Classifier: Environment :: Console
Classifier: Intended Audience :: Science/Research
Classifier: License :: OSI Approved :: BSD License
Classifier: Natural Language :: English
Classifier: Programming Language :: Python :: 3.6
Classifier: Programming Language :: Python :: 3.7
Classifier: Programming Language :: Python :: 3.8
Requires-Python: >=3.6
Requires-Dist: streamlit
Requires-Dist: scipy
Requires-Dist: pandas
Requires-Dist: numpy
Requires-Dist: altair
